faststream_compressors/__init__.py
faststream_compressors/compressors/__init__.py
faststream_compressors/compressors/gzip.py
faststream_compressors/compressors/lz4.py
faststream_compressors/errors.py
faststream_compressors/handler.py
faststream_compressors/middlewares/__init__.py
faststream_compressors/middlewares/nats.py
faststream_compressors-0.2.1.dist-info/METADATA
faststream_compressors-0.2.1.dist-info/WHEEL
faststream_compressors-0.2.1.dist-info/RECORD
