Metadata-Version: 2.1
Name: faststream-compressors
Version: 0.2.1
Summary: A middleware for the FastStream framework to support message compression.
Home-page: https://github.com/ulbwa/faststream-compressors
Author: ульба
Author-email: ulbwa@icloud.com
Requires-Python: >=3.11,<4.0
Classifier: Programming Language :: Python :: 3
Classifier: Programming Language :: Python :: 3.11
Classifier: Programming Language :: Python :: 3.12
Provides-Extra: lz4
Requires-Dist: faststream (>=0.5.18,<0.6.0)
Requires-Dist: lz4 (>=4.3.3,<5.0.0) ; extra == "lz4"
Project-URL: Repository, https://github.com/ulbwa/faststream-compressors
